athesa/__init__.py
athesa/version.py
athesa/adapters/__init__.py
athesa/adapters/selenium/__init__.py
athesa/adapters/selenium/bridge.py
athesa/core/__init__.py
athesa/core/action.py
athesa/core/bridge.py
athesa/core/context.py
athesa/core/handler.py
athesa/core/process.py
athesa/core/screen.py
athesa/core/state.py
athesa/engine/__init__.py
athesa/engine/action_executor.py
athesa/engine/page_detector.py
athesa/engine/process_runner.py
athesa/engine/process_runner_config.py
athesa/engine/state_machine.py
athesa/engine/commands/__init__.py
athesa/engine/commands/handlers.py
athesa/engine/commands/protocol.py
athesa/engine/commands/registry.py
athesa/engine/services/__init__.py
athesa/engine/services/outcome_classifier.py
athesa/engine/services/process_execution_coordinator.py
athesa/engine/services/recovery_service.py
athesa/engine/services/state_transition_service.py
athesa/engine/strategies/__init__.py
athesa/engine/strategies/implementations.py
athesa/engine/strategies/protocol.py
athesa/engine/strategies/registry.py
athesa/events/__init__.py
athesa/events/callbacks.py
athesa/events/emitter.py
athesa/exceptions/__init__.py
athesa/exceptions/errors.py
athesa/factory/__init__.py
athesa/factory/registry.py
athesa-0.1.2.dist-info/licenses/LICENSE
athesa-0.1.2.dist-info/METADATA
athesa-0.1.2.dist-info/WHEEL
athesa-0.1.2.dist-info/top_level.txt
athesa-0.1.2.dist-info/RECORD
