Metadata-Version: 2.4
Name: athesa
Version: 0.1.2
Summary: State-driven web automation framework for complex workflows
Author: Athesa Contributors
License: MIT
Project-URL: Homepage, https://github.com/ixmb/athesa
Project-URL: Documentation, https://github.com/ixmb/athesa#readme
Project-URL: Repository, https://github.com/ixmb/athesa
Project-URL: Issues, https://github.com/ixmb/athesa/issues
Keywords: automation,web,selenium,playwright,state-machine,workflow
Classifier: Development Status :: 3 - Alpha
Classifier: Intended Audience :: Developers
Classifier: License :: OSI Approved :: MIT License
Classifier: Programming Language :: Python :: 3
Classifier: Programming Language :: Python :: 3.9
Classifier: Programming Language :: Python :: 3.10
Classifier: Programming Language :: Python :: 3.11
Classifier: Programming Language :: Python :: 3.12
Classifier: Topic :: Software Development :: Testing
Classifier: Topic :: Software Development :: Libraries :: Python Modules
Requires-Python: >=3.9
License-File: LICENSE
Requires-Dist: selenium>=4.0.0
Requires-Dist: undetected-chromedriver>=3.5.0
Provides-Extra: dev
Requires-Dist: pytest>=7.0.0; extra == "dev"
Requires-Dist: pytest-cov>=4.0.0; extra == "dev"
Requires-Dist: black>=23.0.0; extra == "dev"
Requires-Dist: ruff>=0.1.0; extra == "dev"
Requires-Dist: mypy>=1.0.0; extra == "dev"
Provides-Extra: playwright
Requires-Dist: playwright>=1.40.0; extra == "playwright"
Dynamic: license-file
